dtocean_hydrodynamics/__init__.py
dtocean_hydrodynamics-3.2.0.dist-info/METADATA
dtocean_hydrodynamics-3.2.0.dist-info/WHEEL
dtocean_hydrodynamics-3.2.0.dist-info/RECORD
